Workbook

Sheet Summary
A1: Sun Pharma - Organon: Summary and Recommendation
A2: Snapshot date 2026-08-06. See the companion notebooks (01-09) for full methodology and every intermediate step.
A5: Deal
A6: Sun Pharmaceutical Industries agreeing to acquire Organon & Co for $14.00/share, all cash
A7: (102.9% premium to the 9-Apr-2026 unaffected close). Announced 26-Apr-2026, shareholder
A8: approval obtained 23-Jul-2026, expected close early 2027.
A10: Is the price fair?
A11: Standalone DCF value/share (market-cross-validated discount rate) | C11: ='DCF'!$B$32 -> 6.8976972
A12: Offer price | C12: =Inputs!$B$5 -> 14
A13: Revenue growth the offer requires (vs. actual -0.38% 2yr CAGR) | C13: ='Reverse DCF'!$B$4 -> 0.0387
A14: Implied synergy / growth premium (USD) | C14: ='Reverse DCF'!$B$30 -> 1.8625886e+09
A15: as % of standalone EV | C15: ='Reverse DCF'!$B$31 -> 0.1884944
A16: Acquirer (Sun Pharma) CAR around announcement (-5,+5) - POSITIVE and significant: +9.6%, t=2.64 (source: notebook 05)
A17: Verdict: not a simple overpay story, nor an obvious bargain - a real but plausible growth ask
A19: Should the spread be traded today?
A20: Gross spread | C20: ='Merger Arbitrage'!$B$6 -> 0.031687546
A21: Spread-implied P(completion) | C21: ='Merger Arbitrage'!$B$13 -> 0.93943662
A22: Breakeven P(completion) | C22: ='Merger Arbitrage'!$B$20 -> 0.93943662
A23: Monte Carlo mean return - BELOW the risk-free rate (notebook 07) | C23: ='Merger Arbitrage'!$B$23 -> -0.0104
A24: Max-Sharpe allocation to the arb position (vs. S&P 500) | C24: ='Merger Arbitrage'!$B$28 -> 0
A26: Recommendation
A27: PASS on the unhedged spread at today's price - conditional, not categorical.
A28: The trade only clears a reasonable risk/reward bar if the true completion probability is
A29: close to the market's own implied level rather than the more conservative Monte Carlo
A30: assumption. Shareholder approval is already obtained and the acquirer's own stock reaction
A31: was positive - both lean toward the more optimistic read. This project did NOT verify what
A32: regulatory or other closing conditions remain outstanding as of the snapshot date - that gap
A33: should be closed before sizing real capital against either probability estimate here.
A34: If a position is taken, the correctly-priced hedge is a protective put at the pre-leak
A35: volatility regime, not one calibrated to the deal-pinned volatility the market now quotes.
A36: Put premium, K=$6.90, priced at pre-leak vol | C36: =Derivatives!$B$13 -> 0.079817405

Sheet Inputs
A1: Sun Pharma – Organon: Model Inputs
A2: All cells in this tab are source data (SEC EDGAR / Yahoo Finance, snapshot 2026-08-06). Every other tab references these cells by formula - nothing downstream is a typed-in number.
A4: Deal terms | B4: Value | C4: Source
A5: Offer price (USD/share) | B5: 14 | C5: Organon 8-K Ex-99.1, filed 2026-04-27
A6: Deal enterprise value (USD bn) | B6: 11.75 | C6: Organon 8-K Ex-99.1
A7: Shares outstanding | B7: 262609433 | C7: Yahoo Finance, sharesOutstanding
A8: Announcement date | B8: 2026-04-26 | C8: Organon 8-K Ex-99.1
A9: Reference/leak date | B9: 2026-01-16 | C9: Organon 8-K Ex-99.1 ("before news of takeover interest emerged")
A10: Unaffected date | B10: 2026-04-09 | C10: Organon 8-K Ex-99.1
A11: Shareholder approval date | B11: 2026-07-23 | C11: SEC DEFA14A filings
A13: Market data (snapshot 2026-08-06) | B13: Value | C13: Source
A14: OGN spot price (USD) | B14: 13.57 | C14: Yahoo Finance
A15: OGN unaffected price (USD) | B15: 6.9 | C15: Yahoo Finance, close on unaffected date
A16: OGN 16-Jan reference price (USD) | B16: 8.76 | C16: Yahoo Finance
A17: 10Y UST yield, unaffected date | B17: 0.04293 | C17: Yahoo Finance ^TNX
A18: 10Y UST yield, current | B18: 0.04617 | C18: Yahoo Finance ^TNX
A19: Equity risk premium (US, implied) | B19: 0.0445 | C19: Damodaran, ERP 2026 edition, July 2026 update
A20: OGN beta (pre-leak, 250d) | B20: 0.969 | C20: OLS regression vs S&P 500, notebook 03
A22: Organon FY2025 financials (USD) | B22: Value | C22: Source
A23: Revenue | B23: 6216000000 | C23: SEC 10-K FY2025
A24: EBIT | B24: 929000000 | C24: SEC 10-K FY2025
A25: Normalized tax rate | B25: 0.21 | C25: Yahoo Finance, Tax Rate For Calcs
A26: D&A | B26: 361000000 | C26: SEC 10-K FY2025 cash flow statement
A27: CapEx (negative) | B27: -316000000 | C27: SEC 10-K FY2025 cash flow statement
A28: Change in NWC (negative = use of cash) | B28: -247000000 | C28: SEC 10-K FY2025 cash flow statement
A29: Interest expense | B29: 504000000 | C29: SEC 10-K FY2025
A30: Average total debt (FY24-FY25) | B30: 8762000000 | C30: SEC 10-K, FY2024 and FY2025 balance sheets
A31: Net debt, FY2025 (debt - cash) | B31: 8070000000 | C31: SEC 10-K FY2025 balance sheet
A32: Default spread, B3/B- synthetic rating | B32: 0.055 | C32: Damodaran, interest coverage to rating table (smaller firms)

Sheet Cost of Capital
A1: Cost of Equity, Cost of Debt, WACC
A2: All formulas below reference the Inputs tab. Change any yellow input cell there and this tab recalculates.
A4: Cost of equity (CAPM)
A5: Risk-free rate (unaffected date) | B5: =Inputs!$B$17 -> 0.04293
A6: Beta (pre-leak) | B6: =Inputs!$B$20 -> 0.969
A7: Equity risk premium | B7: =Inputs!$B$19 -> 0.0445
A8: Cost of equity | B8: =B5+B6*B7 -> 0.0860505
A10: Cost of debt: embedded vs marginal
A11: Interest expense (FY2025) | B11: =Inputs!$B$29 -> 504000000
A12: Average total debt | B12: =Inputs!$B$30 -> 8762000000
A13: Embedded pre-tax cost of debt | B13: =B11/B12 -> 0.057521114
A14: Tax rate | B14: =Inputs!$B$25 -> 0.21
A15: Embedded after-tax cost of debt | B15: =B13*(1-B14) -> 0.04544168
A16: EBIT (FY2025) | B16: =Inputs!$B$24 -> 929000000
A17: Interest coverage = EBIT / interest exp. | B17: =B16/B11 -> 1.843254
A18: Default spread (synthetic rating, B3/B-) | B18: =Inputs!$B$32 -> 0.055
A19: Marginal pre-tax cost of debt | B19: =B5+B18 -> 0.09793
A20: Marginal after-tax cost of debt | B20: =B19*(1-B14) -> 0.0773647
A22: WACC
A23: Market cap at unaffected price | B23: =Inputs!$B$15*Inputs!$B$7 -> 1.8120051e+09
A24: Net debt (FY2025) | B24: =Inputs!$B$31 -> 8070000000
A25: Equity weight | B25: =B23/(B23+B24) -> 0.18336411
A26: Debt weight | B26: =1-B25 -> 0.81663589
A27: WACC (embedded cost of debt) | B27: =B25*B8+B26*B15 -> 0.05288788
A28: WACC (marginal/synthetic-rating cost of debt) | B28: =B25*B8+B26*B20 -> 0.078957364
A29: WACC (market-implied - see note) | B29: 0.06607
A31: The market-implied WACC is solved numerically (root-find: the discount rate at which the
A32: flat-revenue DCF below reproduces the $6.90 unaffected price) in the companion notebook -
A33: not reproducible as a single closed-form Excel formula, so it is carried over as a value.
A34: It falls between the embedded and marginal bounds computed live above, which is the check
A35: that validates it. This is the rate the DCF tab below uses.

Sheet DCF
A1: Standalone DCF (flat-revenue base case)
A2: Revenue held flat at the FY2025 level; EBIT margin, D&A, CapEx and NWC investment held at their FY2025 ratio to revenue. Every cell below is a formula.
B4: FY2025 base | C4: Y1 | D4: Y2 | E4: Y3 | F4: Y4 | G4: Y5
A5: Revenue | B5: =Inputs!$B$23 -> 6216000000 | C5: =B5*(1+$B$16) -> 6216000000 | D5: =C5*(1+$B$16) -> 6216000000 | E5: =D5*(1+$B$16) -> 6216000000 | F5: =E5*(1+$B$16) -> 6216000000 | G5: =F5*(1+$B$16) -> 6216000000
A6: EBIT margin | B6: =Inputs!$B$24/Inputs!$B$23 -> 0.14945302 | C6: =Inputs!$B$24/Inputs!$B$23 -> 0.14945302 | D6: =Inputs!$B$24/Inputs!$B$23 -> 0.14945302 | E6: =Inputs!$B$24/Inputs!$B$23 -> 0.14945302 | F6: =Inputs!$B$24/Inputs!$B$23 -> 0.14945302 | G6: =Inputs!$B$24/Inputs!$B$23 -> 0.14945302
A7: EBIT | C7: =C5*C6 -> 9.29e+08 | D7: =D5*D6 -> 9.29e+08 | E7: =E5*E6 -> 9.29e+08 | F7: =F5*F6 -> 9.29e+08 | G7: =G5*G6 -> 9.29e+08
A8: Tax rate | C8: =Inputs!$B$25 -> 0.21 | D8: =Inputs!$B$25 -> 0.21 | E8: =Inputs!$B$25 -> 0.21 | F8: =Inputs!$B$25 -> 0.21 | G8: =Inputs!$B$25 -> 0.21
A9: NOPAT | C9: =C7*(1-C8) -> 7.3391e+08 | D9: =D7*(1-D8) -> 7.3391e+08 | E9: =E7*(1-E8) -> 7.3391e+08 | F9: =F7*(1-F8) -> 7.3391e+08 | G9: =G7*(1-G8) -> 7.3391e+08
A10: D&A (% of revenue) | C10: =C5*(Inputs!$B$26/Inputs!$B$23) -> 361000000 | D10: =D5*(Inputs!$B$26/Inputs!$B$23) -> 361000000 | E10: =E5*(Inputs!$B$26/Inputs!$B$23) -> 361000000 | F10: =F5*(Inputs!$B$26/Inputs!$B$23) -> 361000000 | G10: =G5*(Inputs!$B$26/Inputs!$B$23) -> 361000000
A11: CapEx (% of revenue, negative) | C11: =C5*(Inputs!$B$27/Inputs!$B$23) -> -316000000 | D11: =D5*(Inputs!$B$27/Inputs!$B$23) -> -316000000 | E11: =E5*(Inputs!$B$27/Inputs!$B$23) -> -316000000 | F11: =F5*(Inputs!$B$27/Inputs!$B$23) -> -316000000 | G11: =G5*(Inputs!$B$27/Inputs!$B$23) -> -316000000
A12: Delta NWC (% of revenue, negative) | C12: =C5*(Inputs!$B$28/Inputs!$B$23) -> -247000000 | D12: =D5*(Inputs!$B$28/Inputs!$B$23) -> -247000000 | E12: =E5*(Inputs!$B$28/Inputs!$B$23) -> -247000000 | F12: =F5*(Inputs!$B$28/Inputs!$B$23) -> -247000000 | G12: =G5*(Inputs!$B$28/Inputs!$B$23) -> -247000000
A13: FCFF | C13: =C9+C10+C11+C12 -> 531910000 | D13: =D9+D10+D11+D12 -> 531910000 | E13: =E9+E10+E11+E12 -> 531910000 | F13: =F9+F10+F11+F12 -> 531910000 | G13: =G9+G10+G11+G12 -> 531910000
A15: Assumptions
A16: Revenue growth rate (explicit period) | B16: 0
A17: Terminal growth rate | B17: 0.015
A18: Discount rate (WACC) | B18: ='Cost of Capital'!B29 -> 0.06607
A20: Valuation
A21: Discount factor | C21: =1/(1+$B$18)^1 -> 0.93802471 | D21: =1/(1+$B$18)^2 -> 0.87989035 | E21: =1/(1+$B$18)^3 -> 0.82535889 | F21: =1/(1+$B$18)^4 -> 0.77420703 | G21: =1/(1+$B$18)^5 -> 0.72622532
A22: PV of FCFF | C22: =C13*C21 -> 4.9894472e+08 | D22: =D13*D21 -> 4.6802248e+08 | E22: =E13*E21 -> 4.3901665e+08 | F22: =F13*F21 -> 4.1180846e+08 | G22: =G13*G21 -> 3.8628651e+08
A24: Sum PV of explicit FCFF (Y1-Y5) | B24: =SUM(C22:G22) -> 2.2040788e+09
A25: Terminal value = FCFF_Y5*(1+g)/(WACC-g) | B25: =G13*(1+B17)/(B18-B17) -> 1.0571542e+10
A26: PV of terminal value | B26: =B25*G21 -> 7.6773215e+09
A27: Enterprise value | B27: =B24+B26 -> 9.8814003e+09
A28: Terminal value as % of EV | B28: =B26/B27 -> 0.77694671
A29: Less: net debt (FY2025) | B29: =-Inputs!$B$31 -> -8070000000
A30: Equity value | B30: =B27+B29 -> 1.8114003e+09
A31: Shares outstanding | B31: =Inputs!$B$7 -> 262609433
A32: Equity value per share | B32: =B30/B31 -> 6.8976972
A34: At B16=0% and B18 = the market-implied WACC from the Cost of Capital tab, B32 reproduces the
A35: $6.90 unaffected price by construction (that is how the market-implied WACC was solved). Change
A36: B16 to +3.87% to see the revenue growth path the $14.00 offer requires (see the Reverse DCF tab).

Sheet Sensitivity
A1: Equity Value per Share: WACC x Terminal Growth
A2: Each cell is its own live DCF (same FCFF path as the DCF tab, held flat), evaluated at that row's WACC and that column's terminal growth. No cell is typed in.
A4: WACC \ terminal g | B4: 0 | C4: 0.01 | D4: 0.015 | E4: 0.02 | F4: 0.03
A5: 0.04607 | B5: =(DCF!$C$13/(1+$A5)^1+DCF!$D$13/(1+$A5)^2+DCF!$E$13/(1+$A5)^3+DCF!$F$13/(1+$A5)^4+DCF!$G$13/(1+$A5)^5+(DCF!$G$13*(1+B$4)/($A5-B$4))/(1+$A5)^5-Inputs!$B$31)/Inputs!$B$7 -> 13.235211 | C5: =(DCF!$C$13/(1+$A5)^1+DCF!$D$13/(1+$A5)^2+DCF!$E$13/(1+$A5)^3+DCF!$F$13/(1+$A5)^4+DCF!$G$13/(1+$A5)^5+(DCF!$G$13*(1+C$4)/($A5-C$4))/(1+$A5)^5-Inputs!$B$31)/Inputs!$B$7 -> 23.414572 | D5: =(DCF!$C$13/(1+$A5)^1+DCF!$D$13/(1+$A5)^2+DCF!$E$13/(1+$A5)^3+DCF!$F$13/(1+$A5)^4+DCF!$G$13/(1+$A5)^5+(DCF!$G$13*(1+D$4)/($A5-D$4))/(1+$A5)^5-Inputs!$B$31)/Inputs!$B$7 -> 30.961452 | E5: =(DCF!$C$13/(1+$A5)^1+DCF!$D$13/(1+$A5)^2+DCF!$E$13/(1+$A5)^3+DCF!$F$13/(1+$A5)^4+DCF!$G$13/(1+$A5)^5+(DCF!$G$13*(1+E$4)/($A5-E$4))/(1+$A5)^5-Inputs!$B$31)/Inputs!$B$7 -> 41.403184 | F5: =(DCF!$C$13/(1+$A5)^1+DCF!$D$13/(1+$A5)^2+DCF!$E$13/(1+$A5)^3+DCF!$F$13/(1+$A5)^4+DCF!$G$13/(1+$A5)^5+(DCF!$G$13*(1+F$4)/($A5-F$4))/(1+$A5)^5-Inputs!$B$31)/Inputs!$B$7 -> 81.779616
A6: 0.05607 | B6: =(DCF!$C$13/(1+$A6)^1+DCF!$D$13/(1+$A6)^2+DCF!$E$13/(1+$A6)^3+DCF!$F$13/(1+$A6)^4+DCF!$G$13/(1+$A6)^5+(DCF!$G$13*(1+B$4)/($A6-B$4))/(1+$A6)^5-Inputs!$B$31)/Inputs!$B$7 -> 5.3940739 | C6: =(DCF!$C$13/(1+$A6)^1+DCF!$D$13/(1+$A6)^2+DCF!$E$13/(1+$A6)^3+DCF!$F$13/(1+$A6)^4+DCF!$G$13/(1+$A6)^5+(DCF!$G$13*(1+C$4)/($A6-C$4))/(1+$A6)^5-Inputs!$B$31)/Inputs!$B$7 -> 11.697958 | D6: =(DCF!$C$13/(1+$A6)^1+DCF!$D$13/(1+$A6)^2+DCF!$E$13/(1+$A6)^3+DCF!$F$13/(1+$A6)^4+DCF!$G$13/(1+$A6)^5+(DCF!$G$13*(1+D$4)/($A6-D$4))/(1+$A6)^5-Inputs!$B$31)/Inputs!$B$7 -> 16.001085 | E6: =(DCF!$C$13/(1+$A6)^1+DCF!$D$13/(1+$A6)^2+DCF!$E$13/(1+$A6)^3+DCF!$F$13/(1+$A6)^4+DCF!$G$13/(1+$A6)^5+(DCF!$G$13*(1+E$4)/($A6-E$4))/(1+$A6)^5-Inputs!$B$31)/Inputs!$B$7 -> 21.497204 | F6: =(DCF!$C$13/(1+$A6)^1+DCF!$D$13/(1+$A6)^2+DCF!$E$13/(1+$A6)^3+DCF!$F$13/(1+$A6)^4+DCF!$G$13/(1+$A6)^5+(DCF!$G$13*(1+F$4)/($A6-F$4))/(1+$A6)^5-Inputs!$B$31)/Inputs!$B$7 -> 38.814092
A7: 0.06607 | B7: =(DCF!$C$13/(1+$A7)^1+DCF!$D$13/(1+$A7)^2+DCF!$E$13/(1+$A7)^3+DCF!$F$13/(1+$A7)^4+DCF!$G$13/(1+$A7)^5+(DCF!$G$13*(1+B$4)/($A7-B$4))/(1+$A7)^5-Inputs!$B$31)/Inputs!$B$7 -> -0.073478705 | C7: =(DCF!$C$13/(1+$A7)^1+DCF!$D$13/(1+$A7)^2+DCF!$E$13/(1+$A7)^3+DCF!$F$13/(1+$A7)^4+DCF!$G$13/(1+$A7)^5+(DCF!$G$13*(1+C$4)/($A7-C$4))/(1+$A7)^5-Inputs!$B$31)/Inputs!$B$7 -> 4.159539 | D7: =(DCF!$C$13/(1+$A7)^1+DCF!$D$13/(1+$A7)^2+DCF!$E$13/(1+$A7)^3+DCF!$F$13/(1+$A7)^4+DCF!$G$13/(1+$A7)^5+(DCF!$G$13*(1+D$4)/($A7-D$4))/(1+$A7)^5-Inputs!$B$31)/Inputs!$B$7 -> 6.8976972 | E7: =(DCF!$C$13/(1+$A7)^1+DCF!$D$13/(1+$A7)^2+DCF!$E$13/(1+$A7)^3+DCF!$F$13/(1+$A7)^4+DCF!$G$13/(1+$A7)^5+(DCF!$G$13*(1+E$4)/($A7-E$4))/(1+$A7)^5-Inputs!$B$31)/Inputs!$B$7 -> 10.230203 | F7: =(DCF!$C$13/(1+$A7)^1+DCF!$D$13/(1+$A7)^2+DCF!$E$13/(1+$A7)^3+DCF!$F$13/(1+$A7)^4+DCF!$G$13/(1+$A7)^5+(DCF!$G$13*(1+F$4)/($A7-F$4))/(1+$A7)^5-Inputs!$B$31)/Inputs!$B$7 -> 19.666912
A8: 0.07607 | B8: =(DCF!$C$13/(1+$A8)^1+DCF!$D$13/(1+$A8)^2+DCF!$E$13/(1+$A8)^3+DCF!$F$13/(1+$A8)^4+DCF!$G$13/(1+$A8)^5+(DCF!$G$13*(1+B$4)/($A8-B$4))/(1+$A8)^5-Inputs!$B$31)/Inputs!$B$7 -> -4.1035257 | C8: =(DCF!$C$13/(1+$A8)^1+DCF!$D$13/(1+$A8)^2+DCF!$E$13/(1+$A8)^3+DCF!$F$13/(1+$A8)^4+DCF!$G$13/(1+$A8)^5+(DCF!$G$13*(1+C$4)/($A8-C$4))/(1+$A8)^5-Inputs!$B$31)/Inputs!$B$7 -> -1.0978092 | D8: =(DCF!$C$13/(1+$A8)^1+DCF!$D$13/(1+$A8)^2+DCF!$E$13/(1+$A8)^3+DCF!$F$13/(1+$A8)^4+DCF!$G$13/(1+$A8)^5+(DCF!$G$13*(1+D$4)/($A8-D$4))/(1+$A8)^5-Inputs!$B$31)/Inputs!$B$7 -> 0.77418076 | E8: =(DCF!$C$13/(1+$A8)^1+DCF!$D$13/(1+$A8)^2+DCF!$E$13/(1+$A8)^3+DCF!$F$13/(1+$A8)^4+DCF!$G$13/(1+$A8)^5+(DCF!$G$13*(1+E$4)/($A8-E$4))/(1+$A8)^5-Inputs!$B$31)/Inputs!$B$7 -> 2.9800373 | F8: =(DCF!$C$13/(1+$A8)^1+DCF!$D$13/(1+$A8)^2+DCF!$E$13/(1+$A8)^3+DCF!$F$13/(1+$A8)^4+DCF!$G$13/(1+$A8)^5+(DCF!$G$13*(1+F$4)/($A8-F$4))/(1+$A8)^5-Inputs!$B$31)/Inputs!$B$7 -> 8.8281667
A9: 0.08607 | B9: =(DCF!$C$13/(1+$A9)^1+DCF!$D$13/(1+$A9)^2+DCF!$E$13/(1+$A9)^3+DCF!$F$13/(1+$A9)^4+DCF!$G$13/(1+$A9)^5+(DCF!$G$13*(1+B$4)/($A9-B$4))/(1+$A9)^5-Inputs!$B$31)/Inputs!$B$7 -> -7.1971147 | C9: =(DCF!$C$13/(1+$A9)^1+DCF!$D$13/(1+$A9)^2+DCF!$E$13/(1+$A9)^3+DCF!$F$13/(1+$A9)^4+DCF!$G$13/(1+$A9)^5+(DCF!$G$13*(1+C$4)/($A9-C$4))/(1+$A9)^5-Inputs!$B$31)/Inputs!$B$7 -> -4.9736443 | D9: =(DCF!$C$13/(1+$A9)^1+DCF!$D$13/(1+$A9)^2+DCF!$E$13/(1+$A9)^3+DCF!$F$13/(1+$A9)^4+DCF!$G$13/(1+$A9)^5+(DCF!$G$13*(1+D$4)/($A9-D$4))/(1+$A9)^5-Inputs!$B$31)/Inputs!$B$7 -> -3.6272669 | E9: =(DCF!$C$13/(1+$A9)^1+DCF!$D$13/(1+$A9)^2+DCF!$E$13/(1+$A9)^3+DCF!$F$13/(1+$A9)^4+DCF!$G$13/(1+$A9)^5+(DCF!$G$13*(1+E$4)/($A9-E$4))/(1+$A9)^5-Inputs!$B$31)/Inputs!$B$7 -> -2.0771089 | F9: =(DCF!$C$13/(1+$A9)^1+DCF!$D$13/(1+$A9)^2+DCF!$E$13/(1+$A9)^3+DCF!$F$13/(1+$A9)^4+DCF!$G$13/(1+$A9)^5+(DCF!$G$13*(1+F$4)/($A9-F$4))/(1+$A9)^5-Inputs!$B$31)/Inputs!$B$7 -> 1.8526119
A11: Center cell (row 3, col 3) reproduces the DCF tab's $6.90 by construction.

Sheet Reverse DCF
A1: What Does the $14.00 Offer Require?
A2: Same mechanics as the DCF tab, laid out the same way, but with the revenue growth rate (B6) solved so equity value per share (B21) equals the $14.00 offer. Excel's Goal Seek (Data > What-If Analysis > Goal Seek, set B21 to 14 by changing B6) reproduces this live; the value in B6 is carried over from the notebook's root-find for a static file, and B21 below checks it.
A4: Revenue growth rate (solved to hit $14.00) | B4: 0.0387
A5: Terminal growth rate (held at DCF tab's base case) | B5: =DCF!$B$17 -> 0.015
A6: Discount rate (held at DCF tab's base case) | B6: =DCF!$B$18 -> 0.06607
B8: FY2025 base | C8: Y1 | D8: Y2 | E8: Y3 | F8: Y4 | G8: Y5
A9: Revenue | B9: =Inputs!$B$23 -> 6216000000 | C9: =B9*(1+$B$4) -> 6456559200 | D9: =C9*(1+$B$4) -> 6.706428e+09 | E9: =D9*(1+$B$4) -> 6.9659668e+09 | F9: =E9*(1+$B$4) -> 7.2355497e+09 | G9: =F9*(1+$B$4) -> 7.5155655e+09
A10: EBIT margin (held at DCF tab's FY2025 level) | C10: =DCF!$B$6 -> 0.14945302 | D10: =DCF!$B$6 -> 0.14945302 | E10: =DCF!$B$6 -> 0.14945302 | F10: =DCF!$B$6 -> 0.14945302 | G10: =DCF!$B$6 -> 0.14945302
A11: EBIT | C11: =C9*C10 -> 9.649523e+08 | D11: =D9*D10 -> 1.002296e+09 | E11: =E9*E10 -> 1.0410848e+09 | F11: =F9*F10 -> 1.0813748e+09 | G11: =G9*G10 -> 1.123224e+09
A12: Tax rate | C12: =Inputs!$B$25 -> 0.21 | D12: =Inputs!$B$25 -> 0.21 | E12: =Inputs!$B$25 -> 0.21 | F12: =Inputs!$B$25 -> 0.21 | G12: =Inputs!$B$25 -> 0.21
A13: NOPAT | C13: =C11*(1-C12) -> 7.6231232e+08 | D13: =D11*(1-D12) -> 7.918138e+08 | E13: =E11*(1-E12) -> 8.22457e+08 | F13: =F11*(1-F12) -> 8.5428608e+08 | G13: =G11*(1-G12) -> 8.8734696e+08
A14: D&A (% of revenue) | C14: =C9*(Inputs!$B$26/Inputs!$B$23) -> 374970700 | D14: =D9*(Inputs!$B$26/Inputs!$B$23) -> 3.8948207e+08 | E14: =E9*(Inputs!$B$26/Inputs!$B$23) -> 4.0455502e+08 | F14: =F9*(Inputs!$B$26/Inputs!$B$23) -> 4.202113e+08 | G14: =G9*(Inputs!$B$26/Inputs!$B$23) -> 4.3647348e+08
A15: CapEx (% of revenue, negative) | C15: =C9*(Inputs!$B$27/Inputs!$B$23) -> -328229200 | D15: =D9*(Inputs!$B$27/Inputs!$B$23) -> -3.4093167e+08 | E15: =E9*(Inputs!$B$27/Inputs!$B$23) -> -3.5412573e+08 | F15: =F9*(Inputs!$B$27/Inputs!$B$23) -> -3.6783039e+08 | G15: =G9*(Inputs!$B$27/Inputs!$B$23) -> -3.8206543e+08
A16: Delta NWC (% of revenue, negative) | C16: =C9*(Inputs!$B$28/Inputs!$B$23) -> -256558900 | D16: =D9*(Inputs!$B$28/Inputs!$B$23) -> -2.6648773e+08 | E16: =E9*(Inputs!$B$28/Inputs!$B$23) -> -2.768008e+08 | F16: =F9*(Inputs!$B$28/Inputs!$B$23) -> -2.87513e+08 | G16: =G9*(Inputs!$B$28/Inputs!$B$23) -> -2.9863975e+08
A17: FCFF | C17: =C13+C14+C15+C16 -> 552494917 | D17: =D13+D14+D15+D16 -> 5.7387647e+08 | E17: =E13+E14+E15+E16 -> 5.9608549e+08 | F17: =F13+F14+F15+F16 -> 6.19154e+08 | G17: =G13+G14+G15+G16 -> 6.4311526e+08
A18: Discount factor | C18: =1/(1+$B$6)^1 -> 0.93802471 | D18: =1/(1+$B$6)^2 -> 0.87989035 | E18: =1/(1+$B$6)^3 -> 0.82535889 | F18: =1/(1+$B$6)^4 -> 0.77420703 | G18: =1/(1+$B$6)^5 -> 0.72622532
A19: PV of FCFF | C19: =C17*C18 -> 5.1825388e+08 | D19: =D17*D18 -> 5.0494837e+08 | E19: =E17*E18 -> 4.9198446e+08 | F19: =F17*F18 -> 4.7935338e+08 | G19: =G17*G18 -> 4.6704659e+08
A20: Sum PV of explicit FCFF (Y1-Y5) | B20: =SUM(C19:G19) -> 2.4615867e+09
A21: Terminal value | B21: =G17*(1+B5)/(B6-B5) -> 1.2781711e+10
A22: PV of terminal value | B22: =B21*G18 -> 9.2824023e+09
A23: Enterprise value (implied by this growth path) | B23: =B20+B22 -> 1.1743989e+10
A24: Less: net debt | B24: =-Inputs!$B$31 -> -8070000000
A25: Equity value | B25: =B23+B24 -> 3.673989e+09
A26: Shares outstanding | B26: =Inputs!$B$7 -> 262609433
A27: Equity value per share (check: should be ~$14.00) | B27: =B25/B26 -> 13.990316
A29: Standalone EV (0% growth base case, from DCF tab) | B29: =DCF!$B$27 -> 9.8814003e+09
A30: Implied synergy / growth premium | B30: =B23-B29 -> 1.8625886e+09
A31: As % of standalone EV | B31: =B30/B29 -> 0.1884944
A33: FY2023 revenue (historical fact, not derived elsewhere in this workbook) | B33: 6263000000
A34: Actual FY2023-to-FY2025 revenue CAGR (2-year span), for comparison | B34: =(Inputs!$B$23/B33)^0.5-1 -> -0.0037592615

Sheet Merger Arbitrage
A1: Spread, Implied Probability, Expected Value
A2: Spot, offer and break-price scenarios drive every formula below. Monte Carlo and Sharpe/Treynor results (which need a full return-series regression and 100,000 simulated paths - not reproducible as a handful of spreadsheet formulas) are carried over from the companion notebook, sourced explicitly where used.
A4: Spot price | B4: =Inputs!$B$14 -> 13.57
A5: Offer price | B5: =Inputs!$B$5 -> 14
A6: Gross spread | B6: =B5/B4-1 -> 0.031687546
A8: Break-price scenarios
A9: Break price: unaffected basis | B9: =Inputs!$B$15 -> 6.9
A10: Break price: unaffected -10% | B10: =B9*0.9 -> 6.21
A11: Break price: unaffected -20% | B11: =B9*0.8 -> 5.52
A13: Spread-implied P(completion), unaffected basis | B13: =(B4-B9)/(B5-B9) -> 0.93943662
A14: Spread-implied P(completion), -10% basis | B14: =(B4-B10)/(B5-B10) -> 0.94480103
A15: Spread-implied P(completion), -20% basis | B15: =(B4-B11)/(B5-B11) -> 0.94929245
A17: Downside if deal breaks (unaffected basis) | B17: =B9/B4-1 -> -0.49152542
A18: Upside if deal completes | B18: =B5/B4-1 -> 0.031687546
A20: Breakeven P(completion) (unaffected basis) | B20: =-B17/(B18-B17) -> 0.93943662
A22: From companion notebook (100,000-path Monte Carlo)
A23: Mean holding-period return | B23: -0.0104
A24: Probability of a loss | B24: 0.0807
A25: 95% VaR | B25: -0.4782
A26: 95% CVaR | B26: -0.5153
A27: Position beta vs S&P 500 (since announcement) | B27: 0.049
A28: Max-Sharpe two-asset mix: weight on arb position | B28: 0

Sheet Derivatives
A1: Black-Scholes Put Pricing, Built Natively in Excel
A2: OGN's own listed options were checked directly and found unusable (zero bid/ask, zero open interest at the money, across OGN and every large US pharma peer checked) - see the companion notebook. Priced here from first principles instead, using the standard normal CDF, with the pre-leak realised volatility as the input - not the post-announcement (deal-pinned) volatility, which would price the very risk being insured against as if it barely existed.
A4: Spot (S) | B4: =Inputs!$B$14 -> 13.57
A5: Strike (K) - unaffected price | B5: =Inputs!$B$15 -> 6.9
A6: Risk-free rate (r), current | B6: =Inputs!$B$18 -> 0.04617
A7: Volatility (sigma) - pre-leak regime | B7: 0.5802
A8: Time to expiry (T, years) | B8: 0.529
A10: d1 = (LN(S/K)+(r+0.5*sigma^2)*T)/(sigma*SQRT(T)) | B10: =(LN(B4/B5)+(B6+0.5*B7^2)*B8)/(B7*SQRT(B8)) -> 1.8716012
A11: d2 = d1 - sigma*SQRT(T) | B11: =B10-B7*SQRT(B8) -> 1.4496079
A13: Put premium = K*EXP(-r*T)*NORMSDIST(-d2) - S*NORMSDIST(-d1) | B13: =B5*EXP(-B6*B8)*NORMSDIST(-B11)-B4*NORMSDIST(-B10) -> 0.079817405
A14: Put delta = NORMSDIST(d1) - 1 | B14: =NORMSDIST(B10)-1 -> -0.0306309
A16: Cross-check: same formula at post-announcement vol (4.46%) - shown to be near zero
A17: Volatility (sigma) - post-announcement (circular, for contrast only) | B17: 0.0446
A18: d1 (circular) | B18: =(LN(B4/B5)+(B6+0.5*B17^2)*B8)/(B17*SQRT(B8)) -> 21.618971
A19: d2 (circular) | B19: =B18-B17*SQRT(B8) -> 21.586533
A20: Put premium (circular vol) - shows the understatement | B20: =B5*EXP(-B6*B8)*NORMSDIST(-B19)-B4*NORMSDIST(-B18) -> 0
